quickdiary/__init__.py
quickdiary/__main__.py
quickdiary-0.0.8.dist-info/LICENSE.txt
quickdiary-0.0.8.dist-info/METADATA
quickdiary-0.0.8.dist-info/WHEEL
quickdiary-0.0.8.dist-info/entry_points.txt
quickdiary-0.0.8.dist-info/top_level.txt
quickdiary-0.0.8.dist-info/RECORD
